havina/__init__.py
havina/entity_finding.py
havina/filters.py
havina/graph_generator.py
havina/language_model.py
havina/tests/__init__.py
havina/tests/entity_finding_test.py
havina/tests/filters_test.py
havina/tests/graph_generator_test.py
havina/tests/language_model_test.py
havina-0.1.3.dist-info/METADATA
havina-0.1.3.dist-info/WHEEL
havina-0.1.3.dist-info/licenses/LICENSE
havina-0.1.3.dist-info/RECORD
