Metadata-Version: 2.1
Name: Havina
Version: 0.1.3
Summary: Havina is a Python library that can generate knowledge graphs triplets from an input text. Its implementation is based on the paper "Language models are open knowledge graphs" with some tweaks to improve performance. Havina can be used to evaluate the language comprehension of AI models or as a tool to extract triplets from text and build knowledge graphs.
Project-URL: repository, https://github.com/LucasSte/havina
Author-email: Lucas Steuernagel <lucas.ste@proton.me>
License-Expression: MIT
License-File: LICENSE
Requires-Python: >=3.10
Requires-Dist: coreferee
Requires-Dist: einops
Requires-Dist: spacy
Requires-Dist: spacy-entity-linker
Requires-Dist: spacy-transformers
Requires-Dist: torch
Requires-Dist: transformers==4.30.2
